retnets/__init__.py
retnets-0.0.2.dist-info/METADATA
retnets-0.0.2.dist-info/WHEEL
retnets-0.0.2.dist-info/top_level.txt
retnets-0.0.2.dist-info/RECORD
