Metadata-Version: 2.1
Name: retnets
Version: 0.0.2
Summary: RETNETS is a powerful package designed to facilitate the usage of the Retentive Network by AI engineers. Whether you are working with Torch or Tensorflow, RETNET provides seamless integration and empowers you to harness the potential of Retentive Network for your AI projects.
Download-URL: https://github.com/useCallback/retnets.git
Author: useCallback (Khalfoun Mohamed El Mehdi)
Author-email: <contact.khalfoun@gmail.com>
Project-URL: github, https://github.com/useCallback/retnets.git
Keywords: retnet,retnets,retentive networks,LLM,large language models,ai,artificial intelligence
Classifier: Development Status :: 1 - Planning
Classifier: Intended Audience :: Developers
Classifier: Programming Language :: Python :: 3
Classifier: Operating System :: Unix
Classifier: Operating System :: MacOS :: MacOS X
Classifier: Operating System :: Microsoft :: Windows
Requires-Dist: torch
Requires-Dist: torchscale
Requires-Dist: fairseq
Requires-Dist: apex
Requires-Dist: fairscale
